setup.py
cetup/__init__.py
cetup/cetup.py
cetup.egg-info/PKG-INFO
cetup.egg-info/SOURCES.txt
cetup.egg-info/dependency_links.txt
cetup.egg-info/entry_points.txt
cetup.egg-info/top_level.txt