Metadata-Version: 1.1
Name: cetup
Version: 0.1
Summary: Quick setup tool for C and C++ projects
Home-page: https://github.com/sixten-hilborn/cetup
Author: Sixten Hilborn
Author-email: sixten.hilborn@gmail.com
License: UNKNOWN
Download-URL: https://github.com/sixten-hilborn/cetup/tarball/0.1
Keywords: C,C++
Platform: UNKNOWN
Classifier: Development Status :: 2 - Pre-Alpha
Classifier: Environment :: Console
Classifier: License :: OSI Approved :: MIT License
Classifier: Intended Audience :: Developers
Classifier: Topic :: Software Development :: Code Generators
Classifier: Programming Language :: Python
